pyfeistel/__init__.py
pyfeistel/cipher.py
pyfeistel/modes.py
pyfeistel/sbox.py
pyfeistel-0.1.1.dist-info/METADATA
pyfeistel-0.1.1.dist-info/WHEEL
pyfeistel-0.1.1.dist-info/licenses/LICENSE
pyfeistel-0.1.1.dist-info/RECORD
