Metadata-Version: 2.4
Name: pyfeistel
Version: 0.1.1
Summary: A pure-Python Feistel Network Block Cipher Implementation
Project-URL: Homepage, https://github.com/overcrash66/PyFeistel
Project-URL: Repository, https://github.com/overcrash66/PyFeistel
Author: Wael SAHLI
License: MIT License
License-File: LICENSE
Keywords: block-cipher,cryptography,encryption,feistel
Classifier: Development Status :: 3 - Alpha
Classifier: Intended Audience :: Developers
Classifier: License :: OSI Approved :: MIT License
Classifier: Operating System :: OS Independent
Classifier: Programming Language :: Python :: 3.10
Classifier: Programming Language :: Python :: 3.11
Classifier: Programming Language :: Python :: 3.12
Classifier: Topic :: Security :: Cryptography
Requires-Python: >=3.10
Provides-Extra: dev
Requires-Dist: black; extra == 'dev'
Requires-Dist: mypy; extra == 'dev'
Requires-Dist: ruff; extra == 'dev'
Provides-Extra: test
Requires-Dist: coverage; extra == 'test'
Requires-Dist: hypothesis; extra == 'test'
Requires-Dist: pytest; extra == 'test'
